<?xml version="1.0" encoding="utf-8" ?>
<dwsync>
<file name="_blank.png" server="solucionesoftware.com.mx/httpdocs/siturco/" local="129816709800000000" remote="129816709800000000" />
<file name="alpha.png" server="solucionesoftware.com.mx/httpdocs/siturco/" local="129816709200000000" remote="129816709200000000" />
<file name="bug.eps" server="solucionesoftware.com.mx/httpdocs/siturco/" local="129816709200000000" remote="129816709200000000" />
<file name="image_demo.jpg" server="solucionesoftware.com.mx/httpdocs/siturco/" local="129816709800000000" remote="129816709800000000" />
<file name="image_with_alpha.png" server="solucionesoftware.com.mx/httpdocs/siturco/" local="129816709800000000" remote="129816709800000000" />
<file name="img.png" server="solucionesoftware.com.mx/httpdocs/siturco/" local="129816709800000000" remote="129816709800000000" />
<file name="logo_example.gif" server="solucionesoftware.com.mx/httpdocs/siturco/" local="129816709800000000" remote="129816709800000000" />
<file name="logo_example.jpg" server="solucionesoftware.com.mx/httpdocs/siturco/" local="129816709800000000" remote="129816709800000000" />
<file name="logo_example.png" server="solucionesoftware.com.mx/httpdocs/siturco/" local="129816709800000000" remote="129816709800000000" />
<file name="pelican.ai" server="solucionesoftware.com.mx/httpdocs/siturco/" local="129816709800000000" remote="129816709800000000" />
<file name="tcpdf_cell.png" server="solucionesoftware.com.mx/httpdocs/siturco/" local="129816709800000000" remote="129816709800000000" />
<file name="tcpdf_logo.jpg" server="solucionesoftware.com.mx/httpdocs/siturco/" local="129816709800000000" remote="129816709800000000" />
<file name="tcpdf_signature.png" server="solucionesoftware.com.mx/httpdocs/siturco/" local="129816709800000000" remote="129816709800000000" />
<file name="testsvg.svg" server="solucionesoftware.com.mx/httpdocs/siturco/" local="129816709800000000" remote="129816709800000000" />
<file name="tiger.ai" server="solucionesoftware.com.mx/httpdocs/siturco/" local="129816709800000000" remote="129816709800000000" />
<file name="tux.svg" server="solucionesoftware.com.mx/httpdocs/siturco/" local="129816709800000000" remote="129816709800000000" />
<file name="_blank.png" server="sertull.solucionesoftware.com.mx//httpdocs/" local="129960842400000000" remote="129960842400000000" />
<file name="alpha.png" server="sertull.solucionesoftware.com.mx//httpdocs/" local="129960841800000000" remote="129960841800000000" />
<file name="bug.eps" server="sertull.solucionesoftware.com.mx//httpdocs/" local="129960841800000000" remote="129960841800000000" />
<file name="image_demo.jpg" server="sertull.solucionesoftware.com.mx//httpdocs/" local="129960841800000000" remote="129960841800000000" />
<file name="image_with_alpha.png" server="sertull.solucionesoftware.com.mx//httpdocs/" local="129960841800000000" remote="129960841800000000" />
<file name="img.png" server="sertull.solucionesoftware.com.mx//httpdocs/" local="129960841800000000" remote="129960841800000000" />
<file name="logo_example.gif" server="sertull.solucionesoftware.com.mx//httpdocs/" local="129960841800000000" remote="129960841800000000" />
<file name="logo_example.jpg" server="sertull.solucionesoftware.com.mx//httpdocs/" local="129960841800000000" remote="129960841800000000" />
<file name="logo_example.png" server="sertull.solucionesoftware.com.mx//httpdocs/" local="129960842400000000" remote="129960842400000000" />
<file name="pelican.ai" server="sertull.solucionesoftware.com.mx//httpdocs/" local="129960842400000000" remote="129960842400000000" />
<file name="tcpdf_cell.png" server="sertull.solucionesoftware.com.mx//httpdocs/" local="129960842400000000" remote="129960842400000000" />
<file name="tcpdf_logo.jpg" server="sertull.solucionesoftware.com.mx//httpdocs/" local="129960842400000000" remote="129960842400000000" />
<file name="tcpdf_signature.png" server="sertull.solucionesoftware.com.mx//httpdocs/" local="129960842400000000" remote="129960842400000000" />
<file name="testsvg.svg" server="sertull.solucionesoftware.com.mx//httpdocs/" local="129960842400000000" remote="129960842400000000" />
<file name="tiger.ai" server="sertull.solucionesoftware.com.mx//httpdocs/" local="129960842400000000" remote="129960842400000000" />
<file name="tux.svg" server="sertull.solucionesoftware.com.mx//httpdocs/" local="129960842400000000" remote="129960842400000000" />
<file name="alpha.png" server="edumas.solucionesoftware.com.mx/httpdocs/" local="130094840580000000" remote="130135504800000000" />
<file name="bug.eps" server="edumas.solucionesoftware.com.mx/httpdocs/" local="130094840560000000" remote="130135504800000000" />
<file name="image_demo.jpg" server="edumas.solucionesoftware.com.mx/httpdocs/" local="130094840540000000" remote="130135504800000000" />
<file name="image_with_alpha.png" server="edumas.solucionesoftware.com.mx/httpdocs/" local="130094840500000000" remote="130135504800000000" />
<file name="img.png" server="edumas.solucionesoftware.com.mx/httpdocs/" local="130094840560000000" remote="130135504800000000" />
<file name="logo_example.gif" server="edumas.solucionesoftware.com.mx/httpdocs/" local="130094840560000000" remote="130135504800000000" />
<file name="logo_example.jpg" server="edumas.solucionesoftware.com.mx/httpdocs/" local="130094840500000000" remote="130135504800000000" />
<file name="logo_example.png" server="edumas.solucionesoftware.com.mx/httpdocs/" local="130094840540000000" remote="130135504800000000" />
<file name="pelican.ai" server="edumas.solucionesoftware.com.mx/httpdocs/" local="130094840500000000" remote="130135504800000000" />
<file name="tcpdf_cell.png" server="edumas.solucionesoftware.com.mx/httpdocs/" local="130094840560000000" remote="130135504800000000" />
<file name="tcpdf_logo.jpg" server="edumas.solucionesoftware.com.mx/httpdocs/" local="130094840540000000" remote="130135504800000000" />
<file name="tcpdf_signature.png" server="edumas.solucionesoftware.com.mx/httpdocs/" local="130094840580000000" remote="130135504800000000" />
<file name="testsvg.svg" server="edumas.solucionesoftware.com.mx/httpdocs/" local="130094840520000000" remote="130135504800000000" />
<file name="tiger.ai" server="edumas.solucionesoftware.com.mx/httpdocs/" local="130094840580000000" remote="130135504800000000" />
<file name="tux.svg" server="edumas.solucionesoftware.com.mx/httpdocs/" local="130094840520000000" remote="130135504800000000" />
<file name="_blank.png" server="edumas.solucionesoftware.com.mx/httpdocs/" local="130094840520000000" remote="130135504800000000" />
</dwsync>